LICENSE.txt
MANIFEST.in
README.md
setup.py
config/VERSION
config/requirements-test.txt
config/requirements.txt
facsimile/__init__.py
facsimile/base.py
facsimile/cli.py
facsimile/codec.py
facsimile/definition.py
facsimile/facs.py
facsimile/install.py
facsimile/state.py
facsimile.egg-info/PKG-INFO
facsimile.egg-info/SOURCES.txt
facsimile.egg-info/dependency_links.txt
facsimile.egg-info/not-zip-safe
facsimile.egg-info/requires.txt
facsimile.egg-info/top_level.txt
facsimile/bin/facs
facsimile/bin/version_bump_dev
facsimile/bin/version_merge_release
facsimile/script/copy_virtualenv.sh
facsimile/script/make_virtualenv.sh