Metadata-Version: 1.1
Name: facsimile
Version: 1.0.2
Summary: UNKNOWN
Home-page: https://github.com/20c/facsimile
Author: 20C
Author-email: code@20c.com
License: LICENSE.txt
Platform: UNKNOWN
Classifier: Development Status :: 4 - Beta
Classifier: License :: OSI Approved :: Apache Software License
